camcops_server-2.4.4.data/scripts/camcops_backup_mysql_database
camcops_server-2.4.4.data/scripts/camcops_windows_service
camcops_server-2.4.4.data/scripts/camcops_server_meta
camcops_server-2.4.4.data/scripts/camcops_print_latest_github_version
camcops_server-2.4.4.data/scripts/camcops_fetch_snomed_codes
camcops_server-2.4.4.data/scripts/camcops_server
camcops_server/discarded_upgrade_code.py
camcops_server/camcops_server_core.py
camcops_server/alembic.ini
camcops_server/__init__.py
camcops_server/camcops_server.py
camcops_server/camcops_windows_service.py
camcops_server/camcops_server_meta.py
camcops_server/static/logo_camcops.png
camcops_server/static/__init__.py
camcops_server/static/glyphicons-halflings-regular.woff2
camcops_server/static/favicon_camcops.png
camcops_server/static/logo_local.png
camcops_server/static/jsoneditor/jsonwidget.css
camcops_server/static/jsoneditor/jsoneditor.min.css
camcops_server/static/jsoneditor/jsoneditor.map
camcops_server/static/jsoneditor/jsoneditor.min.js
camcops_server/static/jsoneditor/img/jsoneditor-icons.svg
camcops_server/translations/.gitignore
camcops_server/translations/da_DK/LC_MESSAGES/camcops.mo
camcops_server/tools/__init__.py
camcops_server/tools/print_latest_github_version.py
camcops_server/tools/fetch_snomed_codes.py
camcops_server/extra_strings/icd10depressive.xml
camcops_server/extra_strings/contactlog.xml
camcops_server/extra_strings/qolbasic.xml
camcops_server/extra_strings/ciwa.xml
camcops_server/extra_strings/core10.xml
camcops_server/extra_strings/icd9cm.xml
camcops_server/extra_strings/slums.xml
camcops_server/extra_strings/cpft_lps_resetresponseclock.xml
camcops_server/extra_strings/cgi.xml
camcops_server/extra_strings/cpft_lps_referral.xml
camcops_server/extra_strings/hamd7.xml
camcops_server/extra_strings/icd10.xml
camcops_server/extra_strings/ace3.xml
camcops_server/extra_strings/elixhauserci.xml
camcops_server/extra_strings/apeqpt.xml
camcops_server-2.4.4.dist-info/pydist.json
camcops_server-2.4.4.dist-info/METADATA
camcops_server-2.4.4.dist-info/WHEEL
camcops_server-2.4.4.dist-info/top_level.txt
camcops_server-2.4.4.dist-info/RECORD
camcops_server-2.4.4.dist-info/DESCRIPTION.rst
camcops_server-2.4.4.dist-info/entry_points.txt
