Metadata-Version: 2.0
Name: camcops-server
Version: 2.4.4
Summary: CamCOPS server
Home-page: https://camcops.readthedocs.org/
Author: Rudolf Cardinal
Author-email: rudolf@pobox.com
License: GNU General Public License v3 or later (GPLv3+)
Keywords: cardinal
Platform: UNKNOWN
Classifier: Development Status :: 5 - Production/Stable
Classifier: Intended Audience :: Healthcare Industry
Classifier: Intended Audience :: Science/Research
Classifier: License :: OSI Approved :: GNU General Public License v3 or later (GPLv3+)
Classifier: Natural Language :: English
Classifier: Operating System :: OS Independent
Classifier: Programming Language :: Python :: 3
Classifier: Programming Language :: Python :: 3.6
Classifier: Topic :: Scientific/Engineering :: Medical Science Apps.
Requires-Dist: Babel (==2.8.0)
Requires-Dist: Chameleon (==3.8.1)
Requires-Dist: CherryPy (==18.6.0)
Requires-Dist: Faker (==4.1.1)
Requires-Dist: PyPDF2 (==1.26.0)
Requires-Dist: Pygments (==2.6.1)
Requires-Dist: Wand (==0.6.1)
Requires-Dist: alabaster (==0.7.12)
Requires-Dist: alembic (==1.4.2)
Requires-Dist: amqp (==2.6.0)
Requires-Dist: appdirs (==1.4.4)
Requires-Dist: asteval (==0.9.18)
Requires-Dist: beautifulsoup4 (==4.9.1)
Requires-Dist: cardinal-pythonlib (==1.0.99)
Requires-Dist: celery (==4.4.6)
Requires-Dist: colander (==1.7.0)
Requires-Dist: colorlog (==4.1.0)
Requires-Dist: deform (==2.0.14)
Requires-Dist: distro (==1.3.0)
Requires-Dist: dogpile.cache (==0.9.2)
Requires-Dist: flake8 (==3.8.3)
Requires-Dist: flower (==0.9.4)
Requires-Dist: gunicorn (==20.0.4)
Requires-Dist: hl7 (==0.3.5)
Requires-Dist: isodate (==0.6.0)
Requires-Dist: lockfile (==0.12.2)
Requires-Dist: lxml (==4.6.2)
Requires-Dist: matplotlib (==3.2.2)
Requires-Dist: numpy (==1.19.0)
Requires-Dist: openpyxl (==3.0.4)
Requires-Dist: paginate (==0.5.6)
Requires-Dist: pandas (==1.0.5)
Requires-Dist: pdfkit (==0.6.1)
Requires-Dist: pendulum (==2.1.0)
Requires-Dist: pexpect (==4.8.0)
Requires-Dist: prettytable (==0.7.2)
Requires-Dist: psutil (==5.7.0)
Requires-Dist: py-bcrypt (==0.4)
Requires-Dist: pycap
Requires-Dist: pyexcel-ods3 (==0.5.3)
Requires-Dist: pyexcel-xlsx (==0.5.8)
Requires-Dist: pyparsing (==2.4.7)
Requires-Dist: pyramid (==1.10.4)
Requires-Dist: pyramid-debugtoolbar (==4.6.1)
Requires-Dist: python-dateutil (==2.8.1)
Requires-Dist: sadisplay (==0.4.9)
Requires-Dist: scipy (==1.5.0)
Requires-Dist: scrapy (==2.3.0)
Requires-Dist: semantic-version (==2.8.5)
Requires-Dist: sphinx (==3.1.1)
Requires-Dist: sphinx-rtd-theme (==0.5.0)
Requires-Dist: sqlalchemy (==1.3.18)
Requires-Dist: sqlparse (==0.3.1)
Requires-Dist: statsmodels (==0.11.1)
Requires-Dist: tornado (==6.1)
Requires-Dist: webob (==1.8.6)
